kam_sphinx_lua-0.1.5-py3.8-nspkg.pth
kamshak/sphinx/lua.py
redjack/__init__.py
redjack/sphinx/__init__.py
redjack/sphinx/lua.py
kam_sphinx_lua-0.1.5.dist-info/METADATA
kam_sphinx_lua-0.1.5.dist-info/WHEEL
kam_sphinx_lua-0.1.5.dist-info/namespace_packages.txt
kam_sphinx_lua-0.1.5.dist-info/top_level.txt
kam_sphinx_lua-0.1.5.dist-info/RECORD
