Metadata-Version: 2.1
Name: kam-sphinx-lua
Version: 0.1.5
Summary: UNKNOWN
Home-page: UNKNOWN
Author: UNKNOWN
Author-email: UNKNOWN
License: UNKNOWN
Platform: UNKNOWN
Requires-Dist: Sphinx
